{"cpd00033": -1, "cpd00129": -2, "cpd00041": -5, "cpd00053": -1, "cpd00039": 1, "cpd00066": -1, "cpd00051": -3, "cpd00274": 1, "cpd00069": 1, "cpd00128": -5, "cpd00309": -2, "cpd00130": -3, "cpd00182": -5, "cpd00307": 5, "cpd00207": -5, "cpd00092": -5, "cpd00323": 1, "cpd00117": -2, "cpd00540": 1, "cpd00311": -5, "cpd00133": -1, "cpd00263": 1, "cpd00305": -2, "cpd00246": -3, "cpd00184": 4, "cpd00151": 1, "cpd00281": -4, "cpd00585": 1, "cpd00339": 2, "cpd01831": 3, "cpd01512": -1, "cpd01758": 1, "cpd00851": 1, "cpd00747": 1, "cpd00737": 1, "cpd00762": 3, "cpd00023": -4, "cpd29948": 1, "cpd19196": 2, "cpd00438": 2, "N-alpha-acetyl-lysine": 2, "cpd01191": -2, "cpd00104": -1, "cpd00507": -5, "cpd01217": 4, "cpd00147": -5, "cpd01571": 1, "cpd00446": 1, "N-acetyl-alanine": 2, "cpd00456": 2, "N-acetyl-serine": 2, "2-hydroxy-4-(methylthio)butyric acid": 5, "cpd00489": 2, "cpd00300": 5, "cpd01563": 3, "cpd00477": 1, "cpd00794": -1, "cpd00091": -1}